<bill session="110" type="h" number="3455" updated="2009-01-09T00:07:40-05:00">
	<status><introduced date="1186200000" datetime="2007-08-04"/></status>

	<introduced date="1186200000" datetime="2007-08-04"/>
	<titles>
		<title type="short" as="introduced">21st Century Veterans Equitable Treatment Act</title>
		<title type="official" as="introduced">To amend title 38, United States Code, to provide for a more equitable geographic allocation of funds appropriated to the Department of Veterans Affairs for medical care.</title>
	</titles>
	<sponsor id="400233"/>
	<cosponsors>
		<cosponsor id="412194" joined="2007-08-04"/>
	</cosponsors>
	<actions>
		<action date="1186200000" datetime="2007-08-04"><text>Referred to the House Committee on Veterans' Affairs.</text></action>
		<action date="1186977600" datetime="2007-08-13"><text>Referred to the Subcommittee on Health.</text></action>
	</actions>
	<committees>

	</committees>
	<relatedbills>

	</relatedbills>
	<subjects>

	</subjects>
	<amendments>

	</amendments>
	<summary>
	8/4/2007--Introduced.<br/>21st Century Veterans Equitable Treatment Act - Directs the Secretary of Veterans Affairs to: (1) establish a maximum specialist referral period (the period between a veteran's referral to a specialty clinic of the Department of Veterans Affairs (VA) by a VA primary care physician and the actual appointment with a specialist); and (2) provide appropriate transportation to such appointments for qualified veterans. Requires the Secretary, in any case in which such period is exceeded or in which transportation was not so provided, to promptly provide for such care or transportation from a private source and to reimburse such source at an appropriate rate. Requires expedited reimbursement procedures. Directs the Secretary to include within standards of performance used for measuring VA medical care administration a standard of assessing improvements in appointment waiting times.<br/>
	</summary>
</bill>
