<bill session="110" type="h" number="4004" updated="2009-01-09T01:13:22-05:00">
	<status><introduced date="1193716800" datetime="2007-10-30"/></status>

	<introduced date="1193716800" datetime="2007-10-30"/>
	<titles>
		<title type="official" as="introduced">To amend the Internal Revenue Code of 1986 to exclude from gross income the stipends received for working as an election judge.</title>
	</titles>
	<sponsor id="400207"/>
	<cosponsors>

	</cosponsors>
	<actions>
		<action date="1193716800" datetime="2007-10-30"><text>Referred to the House Committee on Ways and Means.</text></action>
	</actions>
	<committees>

	</committees>
	<relatedbills>

	</relatedbills>
	<subjects>

	</subjects>
	<amendments>

	</amendments>
	<summary>
	10/30/2007--Introduced.<br/>Amends the Internal Revenue Code to exclude from gross income stipends received for service as an election judge for any federal, state, or local election or for completing a training course to become an election judge. Defines &quot;election judge&quot; to include poll workers and other individuals performing similar functions. 
	</summary>
</bill>
