<bill session="110" type="h" number="880" updated="2009-01-08T18:39:11-05:00">
	<status><introduced date="1170824400" datetime="2007-02-07"/></status>

	<introduced date="1170824400" datetime="2007-02-07"/>
	<titles>
		<title type="short" as="introduced">Gang Deterrence and Community Protection Act of 2007</title>
		<title type="official" as="introduced">To amend title 18, United States Code, to reduce violent gang crime and protect law-abiding citizens and communities from violent criminals, and for other purposes.</title>
	</titles>
	<sponsor id="400137"/>
	<cosponsors>
		<cosponsor id="412218" joined="2007-09-07"/>
		<cosponsor id="400381" joined="2007-02-07"/>
		<cosponsor id="400660" joined="2007-03-07"/>
		<cosponsor id="400095" joined="2007-02-27"/>
		<cosponsor id="400154" joined="2007-02-07"/>
		<cosponsor id="400260" joined="2007-03-13"/>
		<cosponsor id="400071" joined="2007-02-07"/>
		<cosponsor id="400040" joined="2007-06-15"/>
		<cosponsor id="400370" joined="2007-03-07"/>
		<cosponsor id="400365" joined="2007-03-07"/>
		<cosponsor id="400055" joined="2007-02-27"/>
		<cosponsor id="400144" joined="2007-02-07"/>
		<cosponsor id="400212" joined="2007-02-27"/>
		<cosponsor id="400076" joined="2007-02-07"/>
		<cosponsor id="412196" joined="2007-06-15"/>
		<cosponsor id="400315" joined="2007-02-07"/>
		<cosponsor id="400141" joined="2007-02-07"/>
		<cosponsor id="400435" joined="2007-02-07"/>
	</cosponsors>
	<actions>
		<action date="1170824400" datetime="2007-02-07"><text>Referred to the House Committee on the Judiciary.</text></action>
		<action date="1172725200" datetime="2007-03-01"><text>Referred to the Subcommittee on Crime, Terrorism, and Homeland Security.</text></action>
	</actions>
	<committees>

	</committees>
	<relatedbills>

	</relatedbills>
	<subjects>

	</subjects>
	<amendments>

	</amendments>
	<summary>
	2/7/2007--Introduced.<br/>Gang Deterrence and Community Protection Act of 2007 - Amends the federal criminal code to modify and expand prohibitions against criminal street gang activity, including forfeiture provisions.<br/>Revises penalties for: (1) interstate or foreign travel or transportation in aid of racketeering enterprises; (2) carjacking; (3) using interstate commerce facilities in the commission of murder-for-hire and other felony crimes of violence; (4) violent crimes in aid of racketeering activity; (5) murder and other violent crimes committed during and in relation to a drug trafficking crime; (6) using interstate commerce facilities to commit multiple murder; and (7) the use of firearms in crimes of violence and drug trafficking.<br/>Amends: (1) the Racketeer Influenced and Corrupt Organizations Act (RICO) to expand the definition of &quot;racketeering activity&quot; to cover interstate murder; and (2) the Violent Crime Control and Law Enforcement Act of 1994 to authorize the use of community-based justice grants to hire additional prosecutors to reduce backlogs and to fund technology, equipment, and training for specified purposes, including to increase the accurate identification and successful prosecution of young violent offenders<br/>Expands: (1) the rebuttable presumption against release of persons charged with firearms offenses; (2) venue in capital cases; and (3) the authority to prosecute juveniles as adults. Sets a 15-year statute of limitations for non-capital felony crimes of violence.<br/>Authorizes the Attorney General to designate specific areas that are located within one or more states as high intensity interstate gang activity areas.<br/>
	</summary>
</bill>
