<bill session="110" type="hc" number="3" updated="2009-01-08T15:26:36-05:00">
	<status><introduced date="1167886800" datetime="2007-01-04"/></status>

	<introduced date="1167886800" datetime="2007-01-04"/>
	<titles>
		<title type="official" as="introduced">Expressing the sense of the Congress that the United States Postal Service should issue commemorative postage stamps honoring Americans who have distinguished themselves by their service in the armed forces of the United States.</title>
	</titles>
	<sponsor id="400095"/>
	<cosponsors>
		<cosponsor id="400384" joined="2007-06-14"/>
		<cosponsor id="400405" joined="2007-06-14"/>
		<cosponsor id="400333" joined="2007-06-14"/>
		<cosponsor id="400259" joined="2007-06-14"/>
	</cosponsors>
	<actions>
		<action date="1167886800" datetime="2007-01-04"><text>Referred to the House Committee on Oversight and Government Reform.</text></action>
	</actions>
	<committees>
		<committee name="House Oversight and Government Reform" subcommittee="" activity="Referral, In Committee" />
	</committees>
	<relatedbills>

	</relatedbills>
	<subjects>
		<term name="Commemorations"/>
		<term name="Air force"/>
		<term name="Armed forces"/>
		<term name="Coast guard"/>
		<term name="Communications"/>
		<term name="Defense policy"/>
		<term name="Marines"/>
		<term name="Military personnel"/>
		<term name="Navy"/>
		<term name="Postage stamps"/>
	</subjects>
	<amendments>

	</amendments>
	<summary>
	1/4/2007--Introduced.<br/>Expresses the sense of Congress that: (1) commemorative postage stamps should be issued by the United States Postal Service honoring Americans who distinguished themselves by their service in the Navy, Air Force, Marine Corps, and Coast Guard, respectively; and (2) the Citizens' Stamp Advisory Committee should recommend to the Postmaster General that such stamps be issued.<br/>
	</summary>
</bill>
