<bill session="110" type="s" number="1465" updated="2009-01-09T14:51:26-05:00">
	<status><introduced date="1179892800" datetime="2007-05-23"/></status>

	<introduced date="1179892800" datetime="2007-05-23"/>
	<titles>
		<title type="official" as="introduced">A bill to amend title XVIII of the Social Security Act to provide for coverage under the Medicare program of certain medical mobility devices approved as class III medical devices.</title>
	</titles>
	<sponsor id="300026"/>
	<cosponsors>
		<cosponsor id="300002" joined="2007-09-20"/>
		<cosponsor id="400064" joined="2007-11-14"/>
		<cosponsor id="300082" joined="2007-05-23"/>
		<cosponsor id="300060" joined="2007-09-18"/>
		<cosponsor id="300024" joined="2007-10-22"/>
		<cosponsor id="300041" joined="2007-05-23"/>
		<cosponsor id="300083" joined="2008-06-09"/>
		<cosponsor id="400054" joined="2007-10-22"/>
		<cosponsor id="400194" joined="2007-09-24"/>
	</cosponsors>
	<actions>
		<action date="1179892800" datetime="2007-05-23"><text>Read twice and referred to the Committee on Finance.</text></action>
	</actions>
	<committees>

	</committees>
	<relatedbills>

	</relatedbills>
	<subjects>

	</subjects>
	<amendments>

	</amendments>
	<summary>
	5/23/2007--Introduced.<br/>Amends title XVIII (Medicare) of the Social Security Act to provide for Medicare coverage of certain medical mobility devices approved as a class III medical device pursuant to a premarket approval application under the Federal Food, Drug, and Cosmetic Act.<br/>
	</summary>
</bill>
