<bill session="110" type="s" number="2003" updated="2009-01-09T15:59:53-05:00">
	<status><introduced date="1186113600" datetime="2007-08-03"/></status>

	<introduced date="1186113600" datetime="2007-08-03"/>
	<titles>
		<title type="official" as="introduced">A bill to facilitate the part-time reemployment of annuitants, and for other purposes.</title>
	</titles>
	<sponsor id="300025"/>
	<cosponsors>
		<cosponsor id="300098" joined="2007-08-03"/>
		<cosponsor id="300099" joined="2007-08-03"/>
	</cosponsors>
	<actions>
		<action date="1186113600" datetime="2007-08-03"><text>Sponsor introductory remarks on measure. (CR S10932-10933)</text></action>
		<action date="1186113600" datetime="2007-08-03"><text>Read twice and referred to the Committee on Homeland Security and Governmental Affairs.</text></action>
		<action date="1187755200" datetime="2007-08-22"><text>Committee on Homeland Security and Governmental Affairs referred to Subcommittee on Oversight of Government Management, the Federal Workforce, and the District of Columbia.</text></action>
	</actions>
	<committees>

	</committees>
	<relatedbills>

	</relatedbills>
	<subjects>

	</subjects>
	<amendments>

	</amendments>
	<summary>
	8/3/2007--Introduced.<br/>Allows a federal agency head to waive the application of civil service retirement system and federal employee retirement system provisions restricting annuities and pay upon reemployment with respect to an annuitant employed as a limited time appointee, but prohibits waiving such provisions with respect to an annuitant for more than: (1) 520 hours of service performed during the six months following the individual's annuity commencing date; (2) 1040 hours of service performed during any 12-month period; or (3) 6240 hours of service performed during the individual's lifetime.<br/>
	</summary>
</bill>
